Commands/__init__.py
Commands/bind.py
Commands/buyplan.py
Commands/check.py
Commands/checkinfo.py
Commands/getapp.py
Commands/idapple.py
Commands/myinfo.py
Commands/myinvite.py
Commands/mysub.py
Commands/myusage.py
Commands/ping.py
Commands/sni.py
Commands/start.py
Commands/topserver.py
Commands/topused.py
Commands/unbind.py
Commands/website.py
Modules/__init__.py
Modules/daily.py
Modules/order.py
Modules/ticket.py
aikopanel_bot-1.3.dist-info/LICENSE
aikopanel_bot-1.3.dist-info/METADATA
aikopanel_bot-1.3.dist-info/WHEEL
aikopanel_bot-1.3.dist-info/entry_points.txt
aikopanel_bot-1.3.dist-info/top_level.txt
aikopanel_bot-1.3.dist-info/RECORD
