Metadata-Version: 2.1
Name: aikopanel-bot
Version: 1.3
Summary: Description of the aikopanel-bot project
Home-page: https://github.com/Github-Aiko/AikoPanel-bot
Author: AikoCute
Author-email: aiko@aikocute.tech
Classifier: Development Status :: 5 - Production/Stable
Classifier: Intended Audience :: Developers
Classifier: License :: OSI Approved :: MIT License
Classifier: Programming Language :: Python :: 3
Classifier: Programming Language :: Python :: 3.6
Classifier: Programming Language :: Python :: 3.7
Classifier: Programming Language :: Python :: 3.8
Classifier: Programming Language :: Python :: 3.9
License-File: LICENSE
Requires-Dist: DBUtils (==3.0.2)
Requires-Dist: pandas (==1.4.2)
Requires-Dist: PyMySQL (==1.0.2)
Requires-Dist: python-telegram-bot (==20.0a4)
Requires-Dist: PyYAML (==6.0)
Requires-Dist: requests (==2.27.1)
Requires-Dist: sshtunnel (==0.4.0)
Requires-Dist: qrcode (==7.4.2)
